{"states":[{"after":{},"afterT":0,"before":{"t":[0,0]},"beforeT":1,"pos":[28,2,6.25,49,0]},{"after":{"t":[0,0]},"afterT":1,"before":{},"beforeT":0,"pos":[28,2,6.25,49,0]},{"after":{},"afterT":0,"before":{"t":[0,0]},"beforeT":1,"pos":[28,2,6.25,49,0]},{"after":{"t":[0,0]},"afterT":1,"before":{},"beforeT":0,"pos":[28,2,6.25,49,0]},{"after":{},"afterT":0,"before":{"t":[0,0]},"beforeT":1,"pos":[30,2,6.25,49,0]},{"after":{"t":[0,0]},"afterT":1,"before":{},"beforeT":0,"pos":[30,2,6.25,49,0]},{"after":{},"afterT":0,"before":{"t":[0,0]},"beforeT":1,"pos":[28,2,6.25,49,0]},{"after":{"t":[0,0]},"afterT":1,"before":{},"beforeT":0,"pos":[28,2,6.25,49,0]},{"after":{},"afterT":0,"before":{"t":[0,0]},"beforeT":1,"pos":[29,2,6.25,49,0]},{"after":{"t":[0,0]},"afterT":1,"before":{},"beforeT":0,"pos":[29,2,6.25,49,0]},{"after":{},"afterT":0,"before":{"t":[0,0]},"beforeT":1,"pos":[30,2,6.25,49,0]},{"after":{"t":[0,0]},"afterT":1,"before":{},"beforeT":0,"pos":[30,2,6.25,49,0]},{"after":{},"afterT":0,"before":{"t":[0,0]},"beforeT":1,"pos":[31,2,6.25,49,0]},{"after":{"t":[0,0]},"afterT":1,"before":{},"beforeT":0,"pos":[31,2,6.25,49,0]},{"after":{},"afterT":0,"before":{"t":[0,0]},"beforeT":1,"pos":[30,2,6.25,49,0]},{"after":{"t":[0,0]},"afterT":1,"before":{},"beforeT":0,"pos":[30,2,6.25,49,0]},{"after":{},"afterT":0,"before":{"t":[0,0]},"beforeT":1,"pos":[33,2,6.25,49,0]},{"after":{"t":[0,0]},"afterT":1,"before":{},"beforeT":0,"pos":[33,2,6.25,49,0]},{"after":{},"afterT":0,"before":{"t":[0,0]},"beforeT":1,"pos":[31,2,6.25,49,0]},{"after":{"t":[0,0]},"afterT":1,"before":{},"beforeT":0,"pos":[31,2,6.25,49,0]},{"after":{},"afterT":0,"before":{"t":[0,0]},"beforeT":1,"pos":[32,2,6.25,49,0]},{"after":{"t":[0,0]},"afterT":1,"before":{},"beforeT":0,"pos":[32,2,6.25,49,0]},{"after":{},"afterT":0,"before":{"t":[0,0]},"beforeT":1,"pos":[33,2,6.25,49,0]},{"after":{"t":[0,0]},"afterT":1,"before":{},"beforeT":0,"pos":[33,2,6.25,49,0]},{"after":{"hp":6.25,"hs":2,"sid":1,"wp":12.5,"ws":1},"afterT":11,"before":{},"beforeT":0,"pos":[42,0,0,49,0]},{"after":{"t":[0,0]},"afterT":1,"before":{},"beforeT":0,"pos":[42,2,6.25,49,0]},{"after":{"hp":6.25,"hs":2,"l":true,"sid":1,"wp":12.5,"ws":1},"afterT":11,"before":{},"beforeT":0,"pos":[43,0,0,49,0]},{"after":{"t":[0,0]},"afterT":1,"before":{},"beforeT":0,"pos":[43,2,6.25,49,0]},{"after":{},"afterT":0,"before":{"t":[0,0]},"beforeT":1,"pos":[42,2,6.25,49,0]},{"after":{"t":[0,0]},"afterT":1,"before":{},"beforeT":0,"pos":[42,2,6.25,49,0]},{"after":{},"afterT":0,"before":{"t":[0,0]},"beforeT":1,"pos":[43,2,6.25,49,0]},{"after":{"t":[0,0]},"afterT":1,"before":{},"beforeT":0,"pos":[43,2,6.25,49,0]},{"after":{"b":true,"hp":6.25,"hs":2,"sid":1,"wp":12.5,"ws":1},"afterT":11,"before":{},"beforeT":0,"pos":[42,0,0,48,0]},{"after":{"t":[0,0]},"afterT":1,"before":{},"beforeT":0,"pos":[42,2,6.25,48,0]},{"after":{},"afterT":0,"before":{"t":[0,0]},"beforeT":1,"pos":[43,2,6.25,49,0]},{"after":{"t":[0,0]},"afterT":1,"before":{},"beforeT":0,"pos":[43,2,6.25,49,0]},{"after":{"hp":6.25,"hs":2,"r":true,"sid":1,"wp":12.5,"ws":1},"afterT":11,"before":{},"beforeT":0,"pos":[41,0,0,48,0]},{"after":{"t":[0,0]},"afterT":1,"before":{},"beforeT":0,"pos":[41,2,6.25,48,0]},{"after":{},"afterT":0,"before":{"t":[0,0]},"beforeT":1,"pos":[42,2,6.25,48,0]},{"after":{"t":[0,0]},"afterT":1,"before":{},"beforeT":0,"pos":[42,2,6.25,48,0]},{"after":{},"afterT":0,"before":{"t":[0,0]},"beforeT":1,"pos":[41,2,6.25,48,0]},{"after":{"t":[0,0]},"afterT":1,"before":{},"beforeT":0,"pos":[41,2,6.25,48,0]},{"after":{},"afterT":0,"before":{"t":[0,0]},"beforeT":1,"pos":[42,2,6.25,48,0]},{"after":{"t":[0,0]},"afterT":1,"before":{},"beforeT":0,"pos":[42,2,6.25,48,0]},{"after":{},"afterT":0,"before":{"t":[0,0]},"beforeT":1,"pos":[41,2,6.25,48,0]},{"after":{"t":[0,0]},"afterT":1,"before":{},"beforeT":0,"pos":[41,2,6.25,48,0]},{"after":{},"afterT":0,"before":{"t":[0,0]},"beforeT":1,"pos":[42,2,6.25,48,0]},{"after":{"t":[0,0]},"afterT":1,"before":{},"beforeT":0,"pos":[42,2,6.25,48,0]},{"after":{},"afterT":0,"before":{"t":[0,0]},"beforeT":1,"pos":[42,2,6.25,48,0]},{"after":{"t":[0,0]},"afterT":1,"before":{},"beforeT":0,"pos":[42,2,6.25,48,0]},{"after":{},"afterT":0,"before":{"t":[0,0]},"beforeT":1,"pos":[42,2,6.25,48,0]},{"after":{"t":[0,0]},"afterT":1,"before":{},"beforeT":0,"pos":[42,2,6.25,48,0]},{"after":{},"afterT":0,"before":{"t":[0,0]},"beforeT":1,"pos":[42,2,6.25,48,0]},{"after":{"t":[0,0]},"afterT":1,"before":{},"beforeT":0,"pos":[42,2,6.25,48,0]},{"after":{},"afterT":0,"before":{"t":[0,0]},"beforeT":1,"pos":[42,2,6.25,48,0]},{"after":{"t":[0,0]},"afterT":1,"before":{},"beforeT":0,"pos":[42,2,6.25,48,0]},{"after":{},"afterT":0,"before":{"t":[0,0]},"beforeT":1,"pos":[43,2,6.25,49,0]},{"after":{"t":[0,0]},"afterT":1,"before":{},"beforeT":0,"pos":[43,2,6.25,49,0]},{"after":{},"afterT":0,"before":{"t":[0,0]},"beforeT":1,"pos":[42,2,6.25,48,0]},{"after":{"t":[0,0]},"afterT":1,"before":{},"beforeT":0,"pos":[42,2,6.25,48,0]},{"after":{},"afterT":0,"before":{"t":[0,0]},"beforeT":1,"pos":[43,2,6.25,49,0]},{"after":{"t":[0,0]},"afterT":1,"before":{},"beforeT":0,"pos":[43,2,6.25,49,0]},{"after":{},"afterT":0,"before":{"t":[0,0]},"beforeT":1,"pos":[43,2,6.25,49,0]},{"after":{"t":[0,0]},"afterT":1,"before":{},"beforeT":0,"pos":[43,2,6.25,49,0]},{"after":{"hp":6.25,"hs":2,"l":true,"sid":1,"wp":12.5,"ws":1},"afterT":11,"before":{},"beforeT":0,"pos":[44,0,0,49,0]},{"after":{"t":[0,0]},"afterT":1,"before":{},"beforeT":0,"pos":[44,2,6.25,49,0]},{"after":{},"afterT":0,"before":{"t":[0,0]},"beforeT":1,"pos":[43,2,6.25,49,0]},{"after":{"t":[0,0]},"afterT":1,"before":{},"beforeT":0,"pos":[43,2,6.25,49,0]},{"after":{},"afterT":0,"before":{"t":[0,0]},"beforeT":1,"pos":[44,2,6.25,49,0]},{"after":{"t":[0,0]},"afterT":1,"before":{},"beforeT":0,"pos":[44,2,6.25,49,0]},{"after":{},"afterT":0,"before":{"t":[0,0]},"beforeT":1,"pos":[44,2,6.25,49,0]},{"after":{"t":[0,0]},"afterT":1,"before":{},"beforeT":0,"pos":[44,2,6.25,49,0]},{"after":{},"afterT":0,"before":{"t":[0,0]},"beforeT":1,"pos":[44,2,6.25,49,0]},{"after":{"t":[0,0]},"afterT":1,"before":{},"beforeT":0,"pos":[44,2,6.25,49,0]},{"after":{},"afterT":0,"before":{"t":[0,0]},"beforeT":1,"pos":[44,2,6.25,49,0]},{"after":{"t":[0,0]},"afterT":1,"before":{},"beforeT":0,"pos":[44,2,6.25,49,0]},{"after":{},"afterT":0,"before":{"t":[0,0]},"beforeT":1,"pos":[44,2,6.25,49,0]},{"after":{"t":[0,0]},"afterT":1,"before":{},"beforeT":0,"pos":[44,2,6.25,49,0]},{"after":{},"afterT":0,"before":{"t":[0,0]},"beforeT":1,"pos":[44,2,6.25,49,0]},{"after":{"t":[0,0]},"afterT":1,"before":{},"beforeT":0,"pos":[44,2,6.25,49,0]},{"after":{},"afterT":0,"before":{"t":[0,0]},"beforeT":1,"pos":[44,2,6.25,49,0]},{"after":{"t":[0,0]},"afterT":1,"before":{},"beforeT":0,"pos":[44,2,6.25,49,0]},{"after":{"hp":6.25,"hs":2,"l":true,"sid":1,"wp":12.5,"ws":1},"afterT":11,"before":{},"beforeT":0,"pos":[45,0,0,49,0]},{"after":{"t":[0,0]},"afterT":1,"before":{},"beforeT":0,"pos":[45,2,6.25,49,0]},{"after":{},"afterT":0,"before":{"t":[0,0]},"beforeT":1,"pos":[44,2,6.25,49,0]},{"after":{"t":[0,0]},"afterT":1,"before":{},"beforeT":0,"pos":[44,2,6.25,49,0]},{"after":{},"afterT":0,"before":{"t":[0,0]},"beforeT":1,"pos":[45,2,6.25,49,0]},{"after":{"t":[0,0]},"afterT":1,"before":{},"beforeT":0,"pos":[45,2,6.25,49,0]},{"after":{},"afterT":0,"before":{"t":[0,0]},"beforeT":1,"pos":[45,2,6.25,49,0]},{"after":{"t":[0,0]},"afterT":1,"before":{},"beforeT":0,"pos":[45,2,6.25,49,0]},{"after":{"hp":6.25,"hs":2,"l":true,"sid":1,"wp":12.5,"ws":1},"afterT":11,"before":{},"beforeT":0,"pos":[46,0,0,49,0]},{"after":{"t":[0,0]},"afterT":1,"before":{},"beforeT":0,"pos":[46,2,6.25,49,0]},{"after":{},"afterT":0,"before":{"t":[0,0]},"beforeT":1,"pos":[45,2,6.25,49,0]},{"after":{"t":[0,0]},"afterT":1,"before":{},"beforeT":0,"pos":[45,2,6.25,49,0]},{"after":{},"afterT":0,"before":{"t":[0,0]},"beforeT":1,"pos":[46,2,6.25,49,0]},{"after":{"t":[0,0]},"afterT":1,"before":{},"beforeT":0,"pos":[46,2,6.25,49,0]},{"after":{},"afterT":0,"before":{"t":[0,0]},"beforeT":1,"pos":[46,2,6.25,49,0]},{"after":{"t":[0,0]},"afterT":1,"before":{},"beforeT":0,"pos":[46,2,6.25,49,0]},{"after":{},"afterT":0,"before":{"t":[0,0]},"beforeT":1,"pos":[46,2,6.25,49,0]},{"after":{"t":[0,0]},"afterT":1,"before":{},"beforeT":0,"pos":[46,2,6.25,49,0]},{"after":{"hp":6.25,"hs":2,"l":true,"sid":1,"wp":12.5,"ws":1},"afterT":11,"before":{},"beforeT":0,"pos":[47,0,0,49,0]},{"after":{"t":[0,0]},"afterT":1,"before":{},"beforeT":0,"pos":[47,2,6.25,49,0]},{"after":{},"afterT":0,"before":{"t":[0,0]},"beforeT":1,"pos":[46,2,6.25,49,0]},{"after":{"t":[0,0]},"afterT":1,"before":{},"beforeT":0,"pos":[46,2,6.25,49,0]},{"after":{},"afterT":0,"before":{"t":[0,0]},"beforeT":1,"pos":[47,2,6.25,49,0]},{"after":{"t":[0,0]},"afterT":1,"before":{},"beforeT":0,"pos":[47,2,6.25,49,0]},{"after":{},"afterT":0,"before":{"t":[0,0]},"beforeT":1,"pos":[47,2,6.25,49,0]},{"after":{"t":[0,0]},"afterT":1,"before":{},"beforeT":0,"pos":[47,2,6.25,49,0]},{"after":{},"afterT":0,"before":{"t":[0,0]},"beforeT":1,"pos":[47,2,6.25,49,0]},{"after":{"t":[0,0]},"afterT":1,"before":{},"beforeT":0,"pos":[47,2,6.25,49,0]},{"after":{},"afterT":0,"before":{"t":[0,0]},"beforeT":1,"pos":[47,2,6.25,49,0]},{"after":{"t":[0,0]},"afterT":1,"before":{},"beforeT":0,"pos":[47,2,6.25,49,0]},{"after":{},"afterT":0,"before":{"t":[0,0]},"beforeT":1,"pos":[47,2,6.25,49,0]},{"after":{"t":[0,0]},"afterT":1,"before":{},"beforeT":0,"pos":[47,2,6.25,49,0]},{"after":{},"afterT":0,"before":{"t":[0,0]},"beforeT":1,"pos":[46,2,6.25,49,0]},{"after":{"t":[0,0]},"afterT":1,"before":{},"beforeT":0,"pos":[46,2,6.25,49,0]},{"after":{},"afterT":0,"before":{"t":[0,0]},"beforeT":1,"pos":[47,2,6.25,49,0]},{"after":{"t":[0,0]},"afterT":1,"before":{},"beforeT":0,"pos":[47,2,6.25,49,0]},{"after":{},"afterT":0,"before":{"t":[0,0]},"beforeT":1,"pos":[46,2,6.25,49,0]},{"after":{"t":[0,0]},"afterT":1,"before":{},"beforeT":0,"pos":[46,2,6.25,49,0]},{"after":{},"afterT":0,"before":{"t":[0,0]},"beforeT":1,"pos":[45,2,6.25,49,0]},{"after":{"t":[0,0]},"afterT":1,"before":{},"beforeT":0,"pos":[45,2,6.25,49,0]},{"after":{},"afterT":0,"before":{"t":[0,0]},"beforeT":1,"pos":[46,2,6.25,49,0]},{"after":{"t":[0,0]},"afterT":1,"before":{},"beforeT":0,"pos":[46,2,6.25,49,0]},{"after":{"b":true,"hp":6.25,"hs":2,"sid":1,"wp":12.5,"ws":1},"afterT":11,"before":{},"beforeT":0,"pos":[45,0,0,48,0]},{"after":{"t":[0,0]},"afterT":1,"before":{},"beforeT":0,"pos":[45,2,6.25,48,0]},{"after":{},"afterT":0,"before":{"t":[0,0]},"beforeT":1,"pos":[45,2,6.25,49,0]},{"after":{"t":[0,0]},"afterT":1,"before":{},"beforeT":0,"pos":[45,2,6.25,49,0]},{"after":{"b":true,"hp":6.25,"hs":2,"r":true,"sid":1,"wp":12.5,"ws":1},"afterT":11,"before":{},"beforeT":0,"pos":[44,0,0,48,0]},{"after":{"t":[0,0]},"afterT":1,"before":{},"beforeT":0,"pos":[44,2,6.25,48,0]},{"after":{},"afterT":0,"before":{"t":[0,0]},"beforeT":1,"pos":[45,2,6.25,48,0]},{"after":{"t":[0,0]},"afterT":1,"before":{},"beforeT":0,"pos":[45,2,6.25,48,0]},{"after":{},"afterT":0,"before":{"t":[0,0]},"beforeT":1,"pos":[44,2,6.25,48,0]},{"after":{"t":[0,0]},"afterT":1,"before":{},"beforeT":0,"pos":[44,2,6.25,48,0]},{"after":{},"afterT":0,"before":{"t":[0,0]},"beforeT":1,"pos":[41,2,6.25,48,0]},{"after":{"t":[0,0]},"afterT":1,"before":{},"beforeT":0,"pos":[41,2,6.25,48,0]},{"after":{},"afterT":0,"before":{"t":[0,0]},"beforeT":1,"pos":[44,2,6.25,48,0]},{"after":{"t":[0,0]},"afterT":1,"before":{},"beforeT":0,"pos":[44,2,6.25,48,0]},{"after":{"b":true,"hp":6.25,"hs":2,"l":true,"r":true,"sid":1,"wp":12.5,"ws":1},"afterT":11,"before":{},"beforeT":0,"pos":[43,0,0,48,0]},{"after":{"t":[0,0]},"afterT":1,"before":{},"beforeT":0,"pos":[43,2,6.25,48,0]},{"after":{},"afterT":0,"before":{"t":[0,0]},"beforeT":1,"pos":[42,2,6.25,48,0]},{"after":{"t":[0,0]},"afterT":1,"before":{},"beforeT":0,"pos":[42,2,6.25,48,0]},{"after":{"hp":6.25,"hs":2,"sid":1,"wp":12.5,"ws":1},"afterT":11,"before":{},"beforeT":0,"pos":[38,0,0,47,0]},{"after":{"t":[0,0]},"afterT":1,"before":{},"beforeT":0,"pos":[38,2,6.25,47,0]},{"after":{},"afterT":0,"before":{"t":[0,0]},"beforeT":1,"pos":[41,2,6.25,48,0]},{"after":{"t":[0,0]},"afterT":1,"before":{},"beforeT":0,"pos":[41,2,6.25,48,0]},{"after":{"hp":6.25,"hs":2,"r":true,"sid":1,"wp":12.5,"ws":1},"afterT":11,"before":{},"beforeT":0,"pos":[40,0,0,48,0]},{"after":{"t":[0,0]},"afterT":1,"before":{},"beforeT":0,"pos":[40,2,6.25,48,0]},{"after":{"hp":6.25,"hs":2,"l":true,"sid":1,"wp":12.5,"ws":1},"afterT":11,"before":{},"beforeT":0,"pos":[39,0,0,47,0]},{"after":{"t":[0,0]},"afterT":1,"before":{},"beforeT":0,"pos":[39,2,6.25,47,0]},{"after":{},"afterT":0,"before":{"t":[0,0]},"beforeT":1,"pos":[38,2,6.25,47,0]},{"after":{"t":[0,0]},"afterT":1,"before":{},"beforeT":0,"pos":[38,2,6.25,47,0]},{"after":{"b":true,"hp":6.25,"hs":2,"sid":1,"t":true,"wp":12.5,"ws":1},"afterT":11,"before":{},"beforeT":0,"pos":[38,0,0,48,0]},{"after":{"t":[0,0]},"afterT":1,"before":{},"beforeT":0,"pos":[38,2,6.25,48,0]},{"after":{},"afterT":0,"before":{"t":[0,0]},"beforeT":1,"pos":[38,2,6.25,47,0]},{"after":{"t":[0,0]},"afterT":1,"before":{},"beforeT":0,"pos":[38,2,6.25,47,0]},{"after":{},"afterT":0,"before":{"t":[0,0]},"beforeT":1,"pos":[38,2,6.25,48,0]},{"after":{"t":[0,0]},"afterT":1,"before":{},"beforeT":0,"pos":[38,2,6.25,48,0]},{"after":{"hp":6.25,"hs":2,"l":true,"r":true,"sid":1,"t":true,"wp":12.5,"ws":1},"afterT":11,"before":{},"beforeT":0,"pos":[39,0,0,48,0]},{"after":{"t":[0,0]},"afterT":1,"before":{},"beforeT":0,"pos":[39,2,6.25,48,0]},{"after":{},"afterT":0,"before":{"t":[0,0]},"beforeT":1,"pos":[38,2,6.25,48,0]},{"after":{"t":[0,0]},"afterT":1,"before":{},"beforeT":0,"pos":[38,2,6.25,48,0]},{"after":{},"afterT":0,"before":{"t":[0,0]},"beforeT":1,"pos":[39,2,6.25,48,0]},{"after":{"t":[0,0]},"afterT":1,"before":{},"beforeT":0,"pos":[39,2,6.25,48,0]},{"after":{},"afterT":0,"before":{"t":[0,0]},"beforeT":1,"pos":[41,2,6.25,48,0]},{"after":{"t":[0,0]},"afterT":1,"before":{},"beforeT":0,"pos":[41,2,6.25,48,0]},{"after":{},"afterT":0,"before":{"t":[0,0]},"beforeT":1,"pos":[39,2,6.25,48,0]},{"after":{"t":[0,0]},"afterT":1,"before":{},"beforeT":0,"pos":[39,2,6.25,48,0]},{"after":{},"afterT":0,"before":{"t":[0,0]},"beforeT":1,"pos":[40,2,6.25,48,0]},{"after":{"t":[0,0]},"afterT":1,"before":{},"beforeT":0,"pos":[40,2,6.25,48,0]},{"after":{},"afterT":0,"before":{"t":[0,0]},"beforeT":1,"pos":[41,2,6.25,48,0]},{"after":{"t":[0,0]},"afterT":1,"before":{},"beforeT":0,"pos":[41,2,6.25,48,0]},{"after":{},"afterT":0,"before":{"t":[0,0]},"beforeT":1,"pos":[43,2,6.25,49,0]},{"after":{"t":[0,0]},"afterT":1,"before":{},"beforeT":0,"pos":[43,2,6.25,49,0]},{"after":{},"afterT":0,"before":{"t":[0,0]},"beforeT":1,"pos":[41,2,6.25,48,0]},{"after":{"t":[0,0]},"afterT":1,"before":{},"beforeT":0,"pos":[41,2,6.25,48,0]},{"after":{},"afterT":0,"before":{"t":[0,0]},"beforeT":1,"pos":[42,2,6.25,48,0]},{"after":{"t":[0,0]},"afterT":1,"before":{},"beforeT":0,"pos":[42,2,6.25,48,0]},{"after":{},"afterT":0,"before":{"t":[0,0]},"beforeT":1,"pos":[43,2,6.25,49,0]},{"after":{"t":[0,0]},"afterT":1,"before":{},"beforeT":0,"pos":[43,2,6.25,49,0]},{"after":{},"afterT":0,"before":{"t":[0,0]},"beforeT":1,"pos":[44,2,6.25,49,0]},{"after":{"t":[0,0]},"afterT":1,"before":{},"beforeT":0,"pos":[44,2,6.25,49,0]},{"after":{},"afterT":0,"before":{"t":[0,0]},"beforeT":1,"pos":[43,2,6.25,49,0]},{"after":{"t":[0,0]},"afterT":1,"before":{},"beforeT":0,"pos":[43,2,6.25,49,0]},{"after":{},"afterT":0,"before":{"t":[0,0]},"beforeT":1,"pos":[44,2,6.25,49,0]},{"after":{"t":[0,0]},"afterT":1,"before":{},"beforeT":0,"pos":[44,2,6.25,49,0]},{"after":{},"afterT":0,"before":{"t":[0,0]},"beforeT":1,"pos":[44,2,6.25,49,0]},{"after":{"t":[0,0]},"afterT":1,"before":{},"beforeT":0,"pos":[44,2,6.25,49,0]},{"after":{},"afterT":0,"before":{"t":[0,0]},"beforeT":1,"pos":[44,2,6.25,49,0]},{"after":{"t":[0,0]},"afterT":1,"before":{},"beforeT":0,"pos":[44,2,6.25,49,0]},{"after":{},"afterT":0,"before":{"t":[0,0]},"beforeT":1,"pos":[44,2,6.25,49,0]},{"after":{"t":[0,0]},"afterT":1,"before":{},"beforeT":0,"pos":[44,2,6.25,49,0]},{"after":{},"afterT":0,"before":{"t":[0,0]},"beforeT":1,"pos":[44,2,6.25,49,0]},{"after":{"t":[0,0]},"afterT":1,"before":{},"beforeT":0,"pos":[44,2,6.25,49,0]},{"after":{},"afterT":0,"before":{"t":[0,0]},"beforeT":1,"pos":[44,2,6.25,49,0]},{"after":{"t":[0,0]},"afterT":1,"before":{},"beforeT":0,"pos":[44,2,6.25,49,0]},{"after":{},"afterT":0,"before":{"t":[0,0]},"beforeT":1,"pos":[44,2,6.25,49,0]},{"after":{"t":[0,0]},"afterT":1,"before":{},"beforeT":0,"pos":[44,2,6.25,49,0]},{"after":{},"afterT":0,"before":{"t":[0,0]},"beforeT":1,"pos":[44,2,6.25,49,0]},{"after":{"t":[0,0]},"afterT":1,"before":{},"beforeT":0,"pos":[44,2,6.25,49,0]},{"after":{},"afterT":0,"before":{"t":[0,0]},"beforeT":1,"pos":[44,2,6.25,49,0]},{"after":{"t":[0,0]},"afterT":1,"before":{},"beforeT":0,"pos":[44,2,6.25,49,0]},{"after":{},"afterT":0,"before":{"t":[0,0]},"beforeT":1,"pos":[44,2,6.25,48,0]},{"after":{"t":[0,0]},"afterT":1,"before":{},"beforeT":0,"pos":[44,2,6.25,48,0]},{"after":{},"afterT":0,"before":{"t":[0,0]},"beforeT":1,"pos":[44,2,6.25,49,0]},{"after":{"t":[0,0]},"afterT":1,"before":{},"beforeT":0,"pos":[44,2,6.25,49,0]},{"after":{},"afterT":0,"before":{"t":[0,0]},"beforeT":1,"pos":[45,2,6.25,48,0]},{"after":{"t":[0,0]},"afterT":1,"before":{},"beforeT":0,"pos":[45,2,6.25,48,0]},{"after":{},"afterT":0,"before":{"t":[0,0]},"beforeT":1,"pos":[44,2,6.25,48,0]},{"after":{"t":[0,0]},"afterT":1,"before":{},"beforeT":0,"pos":[44,2,6.25,48,0]},{"after":{},"afterT":0,"before":{"t":[0,0]},"beforeT":1,"pos":[45,2,6.25,48,0]},{"after":{"t":[0,0]},"afterT":1,"before":{},"beforeT":0,"pos":[45,2,6.25,48,0]},{"after":{},"afterT":0,"before":{"t":[0,0]},"beforeT":1,"pos":[45,2,6.25,48,0]},{"after":{"t":[0,0]},"afterT":1,"before":{},"beforeT":0,"pos":[45,2,6.25,48,0]},{"after":{},"afterT":0,"before":{"t":[0,0]},"beforeT":1,"pos":[45,2,6.25,48,0]},{"after":{"t":[0,0]},"afterT":1,"before":{},"beforeT":0,"pos":[45,2,6.25,48,0]},{"after":{"b":true,"hp":6.25,"hs":2,"l":true,"sid":1,"wp":12.5,"ws":1},"afterT":11,"before":{},"beforeT":0,"pos":[46,0,0,48,0]},{"after":{"t":[0,0]},"afterT":1,"before":{},"beforeT":0,"pos":[46,2,6.25,48,0]},{"after":{},"afterT":0,"before":{"t":[0,0]},"beforeT":1,"pos":[45,2,6.25,48,0]},{"after":{"t":[0,0]},"afterT":1,"before":{},"beforeT":0,"pos":[45,2,6.25,48,0]},{"after":{},"afterT":0,"before":{"t":[0,0]},"beforeT":1,"pos":[46,2,6.25,48,0]},{"after":{"t":[0,0]},"afterT":1,"before":{},"beforeT":0,"pos":[46,2,6.25,48,0]},{"after":{},"afterT":0,"before":{"t":[0,0]},"beforeT":1,"pos":[46,2,6.25,48,0]},{"after":{"t":[0,0]},"afterT":1,"before":{},"beforeT":0,"pos":[46,2,6.25,48,0]},{"after":{"hp":6.25,"hs":2,"sid":1,"wp":12.5,"ws":1},"afterT":11,"before":{},"beforeT":0,"pos":[48,0,0,48,0]},{"after":{"t":[0,0]},"afterT":1,"before":{},"beforeT":0,"pos":[48,2,6.25,48,0]},{"after":{},"afterT":0,"before":{"t":[0,0]},"beforeT":1,"pos":[46,2,6.25,48,0]},{"after":{"t":[0,0]},"afterT":1,"before":{},"beforeT":0,"pos":[46,2,6.25,48,0]},{"after":{"b":true,"hp":6.25,"hs":2,"l":true,"r":true,"sid":1,"wp":12.5,"ws":1},"afterT":11,"before":{},"beforeT":0,"pos":[47,0,0,48,0]},{"after":{"t":[0,0]},"afterT":1,"before":{},"beforeT":0,"pos":[47,2,6.25,48,0]},{"after":{},"afterT":0,"before":{"t":[0,0]},"beforeT":1,"pos":[48,2,6.25,48,0]},{"after":{"t":[0,0]},"afterT":1,"before":{},"beforeT":0,"pos":[48,2,6.25,48,0]},{"after":{},"afterT":0,"before":{"t":[0,0]},"beforeT":1,"pos":[48,2,6.25,48,0]},{"after":{"t":[0,0]},"afterT":1,"before":{},"beforeT":0,"pos":[48,2,6.25,48,0]},{"after":{},"afterT":0,"before":{"t":[0,0]},"beforeT":1,"pos":[48,2,6.25,48,0]},{"after":{"t":[0,0]},"afterT":1,"before":{},"beforeT":0,"pos":[48,2,6.25,48,0]},{"after":{},"afterT":0,"before":{"t":[0,0]},"beforeT":1,"pos":[48,2,6.25,48,0]},{"after":{"t":[0,0]},"afterT":1,"before":{},"beforeT":0,"pos":[48,2,6.25,48,0]},{"after":{"hp":6.25,"hs":2,"l":true,"sid":1,"wp":12.5,"ws":1},"afterT":11,"before":{},"beforeT":0,"pos":[49,0,0,48,0]},{"after":{"t":[0,0]},"afterT":1,"before":{},"beforeT":0,"pos":[49,2,6.25,48,0]},{"after":{},"afterT":0,"before":{"t":[0,0]},"beforeT":1,"pos":[48,2,6.25,48,0]},{"after":{"t":[0,0]},"afterT":1,"before":{},"beforeT":0,"pos":[48,2,6.25,48,0]},{"after":{},"afterT":0,"before":{"t":[0,0]},"beforeT":1,"pos":[49,2,6.25,48,0]},{"after":{"t":[0,0]},"afterT":1,"before":{},"beforeT":0,"pos":[49,2,6.25,48,0]},{"after":{"b":true,"hp":6.25,"hs":2,"sid":1,"wp":12.5,"ws":1},"afterT":11,"before":{},"beforeT":0,"pos":[49,0,0,47,0]},{"after":{"t":[0,0]},"afterT":1,"before":{},"beforeT":0,"pos":[49,2,6.25,47,0]},{"after":{},"afterT":0,"before":{"t":[0,0]},"beforeT":1,"pos":[49,2,6.25,48,0]},{"after":{"t":[0,0]},"afterT":1,"before":{},"beforeT":0,"pos":[49,2,6.25,48,0]},{"after":{},"afterT":0,"before":{"t":[0,0]},"beforeT":1,"pos":[49,2,6.25,47,0]},{"after":{"t":[0,0]},"afterT":1,"before":{},"beforeT":0,"pos":[49,2,6.25,47,0]},{"after":{},"afterT":0,"before":{"t":[0,0]},"beforeT":1,"pos":[49,2,6.25,47,0]},{"after":{"t":[0,0]},"afterT":1,"before":{},"beforeT":0,"pos":[49,2,6.25,47,0]},{"after":{},"afterT":0,"before":{"t":[0,0]},"beforeT":1,"pos":[49,2,6.25,47,0]},{"after":{"t":[0,0]},"afterT":1,"before":{},"beforeT":0,"pos":[49,2,6.25,47,0]},{"after":{},"afterT":0,"before":{"t":[0,0]},"beforeT":1,"pos":[49,2,6.25,47,0]},{"after":{"t":[0,0]},"afterT":1,"before":{},"beforeT":0,"pos":[49,2,6.25,47,0]},{"after":{},"afterT":0,"before":{"t":[0,0]},"beforeT":1,"pos":[49,2,6.25,47,0]},{"after":{"t":[0,0]},"afterT":1,"before":{},"beforeT":0,"pos":[49,2,6.25,47,0]},{"after":{},"afterT":0,"before":{"t":[0,0]},"beforeT":1,"pos":[49,2,6.25,47,0]},{"after":{"t":[0,0]},"afterT":1,"before":{},"beforeT":0,"pos":[49,2,6.25,47,0]},{"after":{},"afterT":0,"before":{"t":[0,0]},"beforeT":1,"pos":[49,2,6.25,47,0]},{"after":{"t":[0,0]},"afterT":1,"before":{},"beforeT":0,"pos":[49,2,6.25,47,0]},{"after":{},"afterT":0,"before":{"t":[0,0]},"beforeT":1,"pos":[49,2,6.25,47,0]},{"after":{"t":[0,0]},"afterT":1,"before":{},"beforeT":0,"pos":[49,2,6.25,47,0]}]}